odoo/addons/sale_order_product_recommendation_packaging_default/README.rst
odoo/addons/sale_order_product_recommendation_packaging_default/__init__.py
odoo/addons/sale_order_product_recommendation_packaging_default/__manifest__.py
odoo/addons/sale_order_product_recommendation_packaging_default/i18n/es.po
odoo/addons/sale_order_product_recommendation_packaging_default/i18n/fr.po
odoo/addons/sale_order_product_recommendation_packaging_default/i18n/it.po
odoo/addons/sale_order_product_recommendation_packaging_default/i18n/sale_order_product_recommendation_packaging_default.pot
odoo/addons/sale_order_product_recommendation_packaging_default/readme/CONFIGURE.md
odoo/addons/sale_order_product_recommendation_packaging_default/readme/CONTRIBUTORS.md
odoo/addons/sale_order_product_recommendation_packaging_default/readme/DESCRIPTION.md
odoo/addons/sale_order_product_recommendation_packaging_default/readme/INSTALL.md
odoo/addons/sale_order_product_recommendation_packaging_default/readme/USAGE.md
odoo/addons/sale_order_product_recommendation_packaging_default/static/description/icon.png
odoo/addons/sale_order_product_recommendation_packaging_default/static/description/index.html
odoo/addons/sale_order_product_recommendation_packaging_default/tests/__init__.py
odoo/addons/sale_order_product_recommendation_packaging_default/tests/test_recommendation.py
odoo/addons/sale_order_product_recommendation_packaging_default/wizards/__init__.py
odoo/addons/sale_order_product_recommendation_packaging_default/wizards/sale_order_recommendation.py
odoo/addons/sale_order_product_recommendation_packaging_default/wizards/sale_order_recommendation_view.xml
odoo_addon_sale_order_product_recommendation_packaging_default-16.0.3.0.1.3.dist-info/METADATA
odoo_addon_sale_order_product_recommendation_packaging_default-16.0.3.0.1.3.dist-info/WHEEL
odoo_addon_sale_order_product_recommendation_packaging_default-16.0.3.0.1.3.dist-info/top_level.txt
odoo_addon_sale_order_product_recommendation_packaging_default-16.0.3.0.1.3.dist-info/RECORD
