Metadata-Version: 2.1
Name: odoo-addon-sale_order_product_recommendation_packaging_default
Version: 16.0.3.0.1.3
Summary: Quickly add recommended products to sale order by packagings
Home-page: https://github.com/OCA/sale-workflow
Author: Moduon, Odoo Community Association (OCA)
Author-email: support@odoo-community.org
License: AGPL-3
Classifier: Programming Language :: Python
Classifier: Framework :: Odoo
Classifier: Framework :: Odoo :: 16.0
Classifier: License :: OSI Approved :: GNU Affero General Public License v3
Classifier: Development Status :: 3 - Alpha
Requires-Python: >=3.10
Requires-Dist: odoo-addon-sale-order-product-recommendation<16.1dev,>=16.0dev
Requires-Dist: odoo-addon-sale-packaging-default<16.1dev,>=16.0dev
Requires-Dist: odoo-addon-web-widget-numeric-step<16.1dev,>=16.0dev
Requires-Dist: odoo<16.1dev,>=16.0a
